grigode_env/__init__.py
grigode_env/environ.py
grigode_env/errors.py
grigode_env/parsers.py
grigode_env/types.py
grigode_env-1.0.1.dist-info/LICENSE
grigode_env-1.0.1.dist-info/METADATA
grigode_env-1.0.1.dist-info/WHEEL
grigode_env-1.0.1.dist-info/top_level.txt
grigode_env-1.0.1.dist-info/RECORD
